mibi_bin_tools/_extract_bin.pyx
mibi_bin_tools/_extract_bin.cpython-312-darwin.so
mibi_bin_tools/type_utils.py
mibi_bin_tools/__init__.py
mibi_bin_tools/panel_utils.py
mibi_bin_tools/bin_files.py
mibi_bin_tools/_extract_bin.c
mibi_bin_tools-0.2.14.dist-info/RECORD
mibi_bin_tools-0.2.14.dist-info/LICENSE
mibi_bin_tools-0.2.14.dist-info/WHEEL
mibi_bin_tools-0.2.14.dist-info/top_level.txt
mibi_bin_tools-0.2.14.dist-info/METADATA
