Metadata-Version: 2.1
Name: mibi-bin-tools
Version: 0.2.14
Summary: Source for extracting .bin files from the commercial MIBI.
Author-email: Angelo Lab <theangelolab@gmail.com>
License: Modified Apache License 2.0
Project-URL: repository, https://github.com/angelolab/mibi-bin-tools
Classifier: Development Status :: 4 - Beta
Classifier: Programming Language :: Cython
Classifier: Programming Language :: Python :: 3
Classifier: Programming Language :: Python :: 3.9
Classifier: Programming Language :: Python :: 3.10
Classifier: Programming Language :: Python :: 3.11
Classifier: Programming Language :: Python :: 3.12
Classifier: License :: OSI Approved :: Apache Software License
Classifier: Topic :: Scientific/Engineering :: Bio-Informatics
Requires-Python: >=3.9
License-File: LICENSE
Requires-Dist: Cython>=3
Requires-Dist: matplotlib>=3
Requires-Dist: numpy>=1.25
Requires-Dist: pandas>=2
Requires-Dist: scikit-image>=0.19
Requires-Dist: alpineer>=0.1.9
Requires-Dist: xarray>=2023
Provides-Extra: test
Requires-Dist: coveralls[toml]; extra == "test"
Requires-Dist: pytest; extra == "test"
Requires-Dist: pytest-cases; extra == "test"
Requires-Dist: pytest-cov; extra == "test"
Requires-Dist: pytest-mock; extra == "test"
Requires-Dist: pytest-pycodestyle; extra == "test"
